MANIFEST.in
setup.py
django_media_manager.egg-info/PKG-INFO
django_media_manager.egg-info/SOURCES.txt
django_media_manager.egg-info/dependency_links.txt
django_media_manager.egg-info/not-zip-safe
django_media_manager.egg-info/requires.txt
django_media_manager.egg-info/top_level.txt
filebrowser/__init__.py
filebrowser/base.py
filebrowser/conf.py
filebrowser/decorators.py
filebrowser/fields.py
filebrowser/forms.py
filebrowser/functions.py
filebrowser/models.py
filebrowser/settings.py
filebrowser/urls.py
filebrowser/views.py
filebrowser/locale/ca/LC_MESSAGES/django.mo
filebrowser/locale/ca/LC_MESSAGES/django.po
filebrowser/locale/de/LC_MESSAGES/django.mo
filebrowser/locale/de/LC_MESSAGES/django.po
filebrowser/locale/es/LC_MESSAGES/django.mo
filebrowser/locale/es/LC_MESSAGES/django.po
filebrowser/locale/fr/LC_MESSAGES/django.mo
filebrowser/locale/fr/LC_MESSAGES/django.po
filebrowser/locale/it/LC_MESSAGES/django.mo
filebrowser/locale/it/LC_MESSAGES/django.po
filebrowser/locale/nl/LC_MESSAGES/django.mo
filebrowser/locale/nl/LC_MESSAGES/django.po
filebrowser/locale/pl/LC_MESSAGES/django.mo
filebrowser/locale/pl/LC_MESSAGES/django.po
filebrowser/locale/ru/LC_MESSAGES/django.mo
filebrowser/locale/ru/LC_MESSAGES/django.po
filebrowser/locale/sr/LC_MESSAGES/django.mo
filebrowser/locale/sr/LC_MESSAGES/django.po
filebrowser/locale/sr_Latn/LC_MESSAGES/django.mo
filebrowser/locale/sr_Latn/LC_MESSAGES/django.po
filebrowser/locale/zh_CN/LC_MESSAGES/django.mo
filebrowser/locale/zh_CN/LC_MESSAGES/django.po
filebrowser/locale/zh_TW/LC_MESSAGES/django.mo
filebrowser/locale/zh_TW/LC_MESSAGES/django.po
filebrowser/management/__init__.py
filebrowser/management/commands/__init__.py
filebrowser/management/commands/version_generator.py
filebrowser/static/admin/inlines.js
filebrowser/static/filebrowser/css/filebrowser.css
filebrowser/static/filebrowser/css/suit-filebrowser.css
filebrowser/static/filebrowser/img/explorer.png
filebrowser/static/filebrowser/img/filebrowser_icon_delete.gif
filebrowser/static/filebrowser/img/filebrowser_icon_delete_hover.gif
filebrowser/static/filebrowser/img/filebrowser_icon_rename.gif
filebrowser/static/filebrowser/img/filebrowser_icon_rename_hover.gif
filebrowser/static/filebrowser/img/filebrowser_icon_select.gif
