Metadata-Version: 1.1
Name: django-media-manager
Version: 3.4.2
Summary: Media-Management with the Django Admin-Interface.
Home-page: https://github.com/oliverseal/django-media-manager
Author: ['Patrick Kranzlmueller', 'Six Foot']
Author-email: dev@6ft.com
License: UNKNOWN
Platform: UNKNOWN
Classifier: Development Status :: 4 - Beta
Classifier: Environment :: Web Environment
Classifier: Intended Audience :: Developers
Classifier: License :: OSI Approved :: BSD License
Classifier: Operating System :: OS Independent
Classifier: Programming Language :: Python
Classifier: Framework :: Django
